bedrock_genai_builder/__init__.py
bedrock_genai_builder/cli.py
bedrock_genai_builder/code_content.py
bedrock_genai_builder-0.0.3.dist-info/LICENSE.txt
bedrock_genai_builder-0.0.3.dist-info/METADATA
bedrock_genai_builder-0.0.3.dist-info/WHEEL
bedrock_genai_builder-0.0.3.dist-info/entry_points.txt
bedrock_genai_builder-0.0.3.dist-info/top_level.txt
bedrock_genai_builder-0.0.3.dist-info/RECORD
